scrapista/__init__.py
scrapista/amazon.py
scrapista/goodreads.py
scrapista/imdb.py
scrapista/wikipedia.py
scrapista/helpers/__init__.py
scrapista/helpers/helpers.py
tests/__init__.py
tests/practice.py
tests/tests.py
scrapista-0.2.2.dist-info/AUTHORS.md
scrapista-0.2.2.dist-info/LICENSE
scrapista-0.2.2.dist-info/METADATA
scrapista-0.2.2.dist-info/WHEEL
scrapista-0.2.2.dist-info/top_level.txt
scrapista-0.2.2.dist-info/RECORD
