Metadata-Version: 2.1
Name: scrapista
Version: 0.2.2
Summary: Scrape most popular websites easily
Home-page: https://github.com/alpnix/scrapista
Author: Alp Niksarlı
Author-email: alp.niksarli@gmail.com
License: MIT
Keywords: python,scrape,amazon,wikipedia,imdb,goodreads,web,data mining,web scraping
Platform: UNKNOWN
Classifier: Development Status :: 1 - Planning
Classifier: Intended Audience :: Developers
Classifier: License :: OSI Approved :: MIT License
Classifier: Programming Language :: Python :: 3
Classifier: Operating System :: Unix
Classifier: Operating System :: MacOS :: MacOS X
Classifier: Operating System :: Microsoft :: Windows
Requires-Dist: requests
Requires-Dist: beautifulsoup4
